LICENSE
README.md
setup.py
NlpToolkit_WordSenseDisambiguation_Cy.egg-info/PKG-INFO
NlpToolkit_WordSenseDisambiguation_Cy.egg-info/SOURCES.txt
NlpToolkit_WordSenseDisambiguation_Cy.egg-info/dependency_links.txt
NlpToolkit_WordSenseDisambiguation_Cy.egg-info/requires.txt
NlpToolkit_WordSenseDisambiguation_Cy.egg-info/top_level.txt
WordSenseDisambiguation/__init__.py
WordSenseDisambiguation/AutoProcessor/__init__.py
WordSenseDisambiguation/AutoProcessor/ParseTree/Lesk.c
WordSenseDisambiguation/AutoProcessor/ParseTree/Lesk.pyx
WordSenseDisambiguation/AutoProcessor/ParseTree/MostFrequentTreeAutoSemantic.c
WordSenseDisambiguation/AutoProcessor/ParseTree/MostFrequentTreeAutoSemantic.pyx
WordSenseDisambiguation/AutoProcessor/ParseTree/RandomTreeAutoSemantic.c
WordSenseDisambiguation/AutoProcessor/ParseTree/RandomTreeAutoSemantic.pyx
WordSenseDisambiguation/AutoProcessor/ParseTree/TreeAutoSemantic.c
WordSenseDisambiguation/AutoProcessor/ParseTree/TreeAutoSemantic.pxd
WordSenseDisambiguation/AutoProcessor/ParseTree/TreeAutoSemantic.pyx
WordSenseDisambiguation/AutoProcessor/ParseTree/__init__.py
WordSenseDisambiguation/AutoProcessor/Sentence/Lesk.c
WordSenseDisambiguation/AutoProcessor/Sentence/Lesk.pyx
WordSenseDisambiguation/AutoProcessor/Sentence/MostFrequentSentenceAutoSemantic.c
WordSenseDisambiguation/AutoProcessor/Sentence/MostFrequentSentenceAutoSemantic.pyx
WordSenseDisambiguation/AutoProcessor/Sentence/RandomSentenceAutoSemantic.c
WordSenseDisambiguation/AutoProcessor/Sentence/RandomSentenceAutoSemantic.pyx
WordSenseDisambiguation/AutoProcessor/Sentence/SentenceAutoSemantic.c
WordSenseDisambiguation/AutoProcessor/Sentence/SentenceAutoSemantic.pxd
WordSenseDisambiguation/AutoProcessor/Sentence/SentenceAutoSemantic.pyx
WordSenseDisambiguation/AutoProcessor/Sentence/TurkishSentenceAutoSemantic.c
WordSenseDisambiguation/AutoProcessor/Sentence/TurkishSentenceAutoSemantic.pyx
WordSenseDisambiguation/AutoProcessor/Sentence/__init__.py
nlptoolkit_wordsensedisambiguation_cy.egg-info/PKG-INFO
nlptoolkit_wordsensedisambiguation_cy.egg-info/SOURCES.txt
nlptoolkit_wordsensedisambiguation_cy.egg-info/dependency_links.txt
nlptoolkit_wordsensedisambiguation_cy.egg-info/requires.txt
nlptoolkit_wordsensedisambiguation_cy.egg-info/top_level.txt