Metadata-Version: 2.4
Name: nlptoolkit-wordsensedisambiguation-cy
Version: 1.0.5
Summary: Word Sense Disambiguation Library
Home-page: https://github.com/StarlangSoftware/WordSenseDisambiguation-Cy
Author: olcaytaner
Author-email: olcay.yildiz@ozyegin.edu.tr
License-File: LICENSE
Requires-Dist: NlpToolkit-AnnotatedTree-Cy
Dynamic: author
Dynamic: author-email
Dynamic: description
Dynamic: description-content-type
Dynamic: home-page
Dynamic: license-file
Dynamic: requires-dist
Dynamic: summary
